trytond/modules/purchase_line_twocolumn/README.rst
trytond/modules/purchase_line_twocolumn/__init__.py
trytond/modules/purchase_line_twocolumn/purchase.fodt
trytond/modules/purchase_line_twocolumn/purchase.py
trytond/modules/purchase_line_twocolumn/purchaseline.py
trytond/modules/purchase_line_twocolumn/purchaseline.xml
trytond/modules/purchase_line_twocolumn/tryton.cfg
trytond/modules/purchase_line_twocolumn/versiondep.txt
trytond/modules/purchase_line_twocolumn/locale/de.po
trytond/modules/purchase_line_twocolumn/locale/en.po
trytond/modules/purchase_line_twocolumn/tests/__init__.py
trytond/modules/purchase_line_twocolumn/tests/test_purchase.py
trytond/modules/purchase_line_twocolumn/view/purchase_line_form.xml
mds_purchase_line_twocolumn-5.0.4.dist-info/METADATA
mds_purchase_line_twocolumn-5.0.4.dist-info/WHEEL
mds_purchase_line_twocolumn-5.0.4.dist-info/entry_points.txt
mds_purchase_line_twocolumn-5.0.4.dist-info/top_level.txt
mds_purchase_line_twocolumn-5.0.4.dist-info/RECORD
