Metadata-Version: 2.1
Name: mds-purchase-line-twocolumn
Version: 5.0.4
Summary: Tryton modules to add a two-column-line-type to purchases.
Home-page: https://www.m-ds.de/
Author: m-ds
Author-email: service@m-ds.de
License: GPL-3
Keywords: tryton purchase column purchaseline
Platform: UNKNOWN
Classifier: Development Status :: 5 - Production/Stable
Classifier: Environment :: Plugins
Classifier: Framework :: Tryton
Classifier: Intended Audience :: Developers
Classifier: Intended Audience :: Customer Service
Classifier: Intended Audience :: Information Technology
Classifier: Topic :: Office/Business
Classifier: Natural Language :: German
Classifier: Natural Language :: English
Classifier: Operating System :: OS Independent
Classifier: License :: OSI Approved :: GNU General Public License (GPL)
Classifier: Programming Language :: Python :: 3.4
Classifier: Programming Language :: Python :: 3.5
Classifier: Programming Language :: Python :: 3.6
Requires-Dist: trytond-purchase (<5.1,>=5.0)
Requires-Dist: mds-account-invoice-line-twocolumn (<=5.1,>=5.0.0)
Requires-Dist: trytond (<5.1,>=5.0)
